focdf/__init__.py
focdf/cdf.py
focdf-0.2.0.dist-info/LICENSE.txt
focdf-0.2.0.dist-info/METADATA
focdf-0.2.0.dist-info/WHEEL
focdf-0.2.0.dist-info/top_level.txt
focdf-0.2.0.dist-info/RECORD
